django_typescript_api/__init__.py
django_typescript_api/admin.py
django_typescript_api/apps.py
django_typescript_api/conf.py
django_typescript_api/models.py
django_typescript_api/tests.py
django_typescript_api/views.py
django_typescript_api/core/inspectors.py
django_typescript_api/core/ir.py
django_typescript_api/core/renderers.py
django_typescript_api/core/strategies.py
django_typescript_api/core/utils.py
django_typescript_api/management/commands/generate_ts_client.py
django_typescript_api/migrations/__init__.py
django_typescript_api/static/django_typescript_api/templates/interface.j2
django_typescript_api-0.1.0rc1.dist-info/licenses/LICENSE
django_typescript_api-0.1.0rc1.dist-info/METADATA
django_typescript_api-0.1.0rc1.dist-info/WHEEL
django_typescript_api-0.1.0rc1.dist-info/top_level.txt
django_typescript_api-0.1.0rc1.dist-info/RECORD
