Metadata-Version: 2.4
Name: django-typescript-api
Version: 0.1.0rc1
Summary: Generate TypeScript clients from Django APIs
Author-email: Py Env Studio Team <contact.shaikh.wasim@gmail.com>
License: MIT License
Requires-Python: >=3.8
License-File: LICENSE
Requires-Dist: Django>=4.0
Requires-Dist: Jinja2
Dynamic: license-file
